MANIFEST.in
README.txt
setup.cfg
setup.py
jw/__init__.py
jw.tustep.egg-info/PKG-INFO
jw.tustep.egg-info/SOURCES.txt
jw.tustep.egg-info/dependency_links.txt
jw.tustep.egg-info/entry_points.txt
jw.tustep.egg-info/namespace_packages.txt
jw.tustep.egg-info/not-zip-safe
jw.tustep.egg-info/paster_plugins.txt
jw.tustep.egg-info/requires.txt
jw.tustep.egg-info/top_level.txt
jw/tustep/README.txt
jw/tustep/__init__.py
jw/tustep/config.py
jw/tustep/configure.zcml
jw/tustep/form.py
jw/tustep/browser/__init__.py
jw/tustep/browser/configure.zcml
jw/tustep/browser/ergebnis.pt
jw/tustep/browser/ergebnis2.pt
jw/tustep/browser/ergebnis3.pt
jw/tustep/browser/tustepform.py
jw/tustep/browser/viewlet.pt
jw/tustep/browser/viewlets.py
jw/tustep/browser/images/tustep_pdffile.png
jw/tustep/content/__init__.py
jw/tustep/content/configure.zcml
jw/tustep/interfaces/__init__.py
jw/tustep/portlets/__init__.py
jw/tustep/portlets/configure.zcml
jw/tustep/profiles/default/factorytool.xml
jw/tustep/profiles/default/metadata.xml
jw/tustep/profiles/default/portlets.xml
jw/tustep/profiles/default/types.xml
jw/tustep/profiles/default/viewlets.xml
jw/tustep/tests/__init__.py
jw/tustep/tests/base.py
jw/tustep/tests/test_doctest.py